oc_delivery_apps/__init__.py
oc_delivery_apps/checksums/Component.py
oc_delivery_apps/checksums/__init__.py
oc_delivery_apps/checksums/apps.py
oc_delivery_apps/checksums/archive_object.py
oc_delivery_apps/checksums/controllers.py
oc_delivery_apps/checksums/models.py
oc_delivery_apps/checksums/migrations/0001_initial.py
oc_delivery_apps/checksums/migrations/0002_auto_20170424_0902.py
oc_delivery_apps/checksums/migrations/0003_auto_20170424_1235.py
oc_delivery_apps/checksums/migrations/0005_fileinfo.py
oc_delivery_apps/checksums/migrations/0006_citypes_is_deliverable.py
oc_delivery_apps/checksums/migrations/0007_locations_revision.py
oc_delivery_apps/checksums/migrations/0008_locations_is_deleted.py
oc_delivery_apps/checksums/migrations/0009_auto_20171204_0100.py
oc_delivery_apps/checksums/migrations/0010_citypegroups_citypeincs.py
oc_delivery_apps/checksums/migrations/0011_remove_citypegroups_rn_gav.py
oc_delivery_apps/checksums/migrations/0012_citypegroups_rn_artifactid.py
oc_delivery_apps/checksums/migrations/0013_auto_20180109_0127.py
oc_delivery_apps/checksums/migrations/0014_migrate_file_incs_data.py
oc_delivery_apps/checksums/migrations/0015_auto_20180126_0332.py
oc_delivery_apps/checksums/migrations/0016_citypeparms.py
oc_delivery_apps/checksums/migrations/0017_historicallocations_history_change_reason.py
oc_delivery_apps/checksums/migrations/0018_auto_20180312_0116.py
oc_delivery_apps/checksums/migrations/0019_auto_20180326_0439.py
oc_delivery_apps/checksums/migrations/0020_cs_prov_migration.py
oc_delivery_apps/checksums/migrations/0021_auto_20180329_0242.py
oc_delivery_apps/checksums/migrations/0022_files_depth_level.py
oc_delivery_apps/checksums/migrations/0023_loc_db_index.py
oc_delivery_apps/checksums/migrations/0024_locations_dup_remove.py
oc_delivery_apps/checksums/migrations/0025_auto_20180412_0740.py
oc_delivery_apps/checksums/migrations/0026_auto_20180416_0413.py
oc_delivery_apps/checksums/migrations/0027_notnull_loc_rev.py
oc_delivery_apps-11.3.2.dist-info/LICENSE
oc_delivery_apps-11.3.2.dist-info/METADATA
oc_delivery_apps-11.3.2.dist-info/WHEEL
oc_delivery_apps-11.3.2.dist-info/top_level.txt
oc_delivery_apps-11.3.2.dist-info/RECORD
