Metadata-Version: 2.1
Name: oc-delivery-apps
Version: 11.3.2
Summary: Models and controllers for dlcontents application
License: LGPLv2
Requires-Python: >=3.6
License-File: LICENSE
Requires-Dist: fs
Requires-Dist: oc-sql-helpers >=1.0.0
Requires-Dist: oc-cdtapi
Requires-Dist: python-magic
Requires-Dist: oc-orm-initializator
Requires-Dist: sqlparse
Requires-Dist: configobj
Requires-Dist: pytz
